<?xml version="1.0" encoding="UTF-8"?><record_update>
    <sys_choice action="INSERT_OR_UPDATE" field="bucket_name" table="var__m_sys_hub_action_input_3ed8d95987a310108d4c4b3de8cb0b0e" version="3">
        <sys_choice action="INSERT_OR_UPDATE">
            <dependent_value/>
            <element>bucket_name</element>
            <hint/>
            <inactive>false</inactive>
            <label>-- None --</label>
            <language>en</language>
            <name>var__m_sys_hub_action_input_3ed8d95987a310108d4c4b3de8cb0b0e</name>
            <sequence>0</sequence>
            <synonyms/>
            <sys_created_by>admin</sys_created_by>
            <sys_created_on>2020-09-28 10:57:31</sys_created_on>
            <sys_domain>global</sys_domain>
            <sys_domain_path>/</sys_domain_path>
            <sys_id>c62f1551872310108d4c4b3de8cb0ba3</sys_id>
            <sys_mod_count>10</sys_mod_count>
            <sys_updated_by>admin</sys_updated_by>
            <sys_updated_on>2020-10-14 05:06:36</sys_updated_on>
            <value/>
        </sys_choice>
        <sys_choice action="INSERT_OR_UPDATE">
            <dependent_value/>
            <element>bucket_name</element>
            <hint/>
            <inactive>false</inactive>
            <label>MyBucket</label>
            <language>en</language>
            <name>var__m_sys_hub_action_input_3ed8d95987a310108d4c4b3de8cb0b0e</name>
            <sequence>1</sequence>
            <synonyms/>
            <sys_created_by>admin</sys_created_by>
            <sys_created_on>2020-10-14 05:06:20</sys_created_on>
            <sys_domain>global</sys_domain>
            <sys_domain_path>/</sys_domain_path>
            <sys_id>b938a21687f710108d4c4b3de8cb0b15</sys_id>
            <sys_mod_count>1</sys_mod_count>
            <sys_updated_by>admin</sys_updated_by>
            <sys_updated_on>2020-10-14 05:06:36</sys_updated_on>
            <value>MyBucket</value>
        </sys_choice>
        <sys_choice action="INSERT_OR_UPDATE">
            <dependent_value/>
            <element>bucket_name</element>
            <hint/>
            <inactive>false</inactive>
            <label>test_bucket</label>
            <language>en</language>
            <name>var__m_sys_hub_action_input_3ed8d95987a310108d4c4b3de8cb0b0e</name>
            <sequence>2</sequence>
            <synonyms/>
            <sys_created_by>admin</sys_created_by>
            <sys_created_on>2020-10-14 05:06:20</sys_created_on>
            <sys_domain>global</sys_domain>
            <sys_domain_path>/</sys_domain_path>
            <sys_id>7538a21687f710108d4c4b3de8cb0b16</sys_id>
            <sys_mod_count>1</sys_mod_count>
            <sys_updated_by>admin</sys_updated_by>
            <sys_updated_on>2020-10-14 05:06:36</sys_updated_on>
            <value>test_bucket</value>
        </sys_choice>
        <sys_choice action="INSERT_OR_UPDATE">
            <dependent_value/>
            <element>bucket_name</element>
            <hint/>
            <inactive>false</inactive>
            <label>test_bucket1</label>
            <language>en</language>
            <name>var__m_sys_hub_action_input_3ed8d95987a310108d4c4b3de8cb0b0e</name>
            <sequence>3</sequence>
            <synonyms/>
            <sys_created_by>admin</sys_created_by>
            <sys_created_on>2020-10-14 05:06:20</sys_created_on>
            <sys_domain>global</sys_domain>
            <sys_domain_path>/</sys_domain_path>
            <sys_id>3138a21687f710108d4c4b3de8cb0b17</sys_id>
            <sys_mod_count>1</sys_mod_count>
            <sys_updated_by>admin</sys_updated_by>
            <sys_updated_on>2020-10-14 05:06:36</sys_updated_on>
            <value>test_bucket1</value>
        </sys_choice>
        <sys_choice action="INSERT_OR_UPDATE">
            <dependent_value/>
            <element>bucket_name</element>
            <hint/>
            <inactive>false</inactive>
            <label>test_bucket2</label>
            <language>en</language>
            <name>var__m_sys_hub_action_input_3ed8d95987a310108d4c4b3de8cb0b0e</name>
            <sequence>4</sequence>
            <synonyms/>
            <sys_created_by>admin</sys_created_by>
            <sys_created_on>2020-10-14 05:06:20</sys_created_on>
            <sys_domain>global</sys_domain>
            <sys_domain_path>/</sys_domain_path>
            <sys_id>f938a21687f710108d4c4b3de8cb0b17</sys_id>
            <sys_mod_count>1</sys_mod_count>
            <sys_updated_by>admin</sys_updated_by>
            <sys_updated_on>2020-10-14 05:06:36</sys_updated_on>
            <value>test_bucket2</value>
        </sys_choice>
        <sys_choice_set action="INSERT_OR_UPDATE">
            <element>bucket_name</element>
            <name>var__m_sys_hub_action_input_3ed8d95987a310108d4c4b3de8cb0b0e</name>
            <sys_class_name>sys_choice_set</sys_class_name>
            <sys_created_by>admin</sys_created_by>
            <sys_created_on>2020-09-28 10:57:31</sys_created_on>
            <sys_id>8e2f1551872310108d4c4b3de8cb0ba3</sys_id>
            <sys_mod_count>0</sys_mod_count>
            <sys_name/>
            <sys_package display_value="Oracle Object Storage Management Spoke" source="sn_osm_spoke">41f00ec2871710108d4c4b3de8cb0b2d</sys_package>
            <sys_policy/>
            <sys_scope display_value="Oracle Object Storage Management Spoke">41f00ec2871710108d4c4b3de8cb0b2d</sys_scope>
            <sys_update_name/>
            <sys_updated_by>admin</sys_updated_by>
            <sys_updated_on>2020-09-28 10:57:31</sys_updated_on>
        </sys_choice_set>
    </sys_choice>
</record_update>
